Workbook

Sheet Assumptions
A1: Meridian Gold & Copper Ltd — Model Assumptions
A3: Assumption | B3: Value
A4: Gold price ($/oz) | B4: 2400
A5: Copper price ($/lb) | B5: 4.5
A6: Gold production (koz/yr) | B6: 320
A7: Copper production (Mlb/yr) | B7: 95
A8: Revenue growth (%/yr) | B8: 0.04
A9: AISC ($/oz gold-eq) | B9: 1350
A10: Cost inflation (%/yr) | B10: 0.03
A11: Tax rate | B11: 0.28
A12: Discount rate (WACC) | B12: 0.09
A13: Terminal growth rate | B13: 0.02
A15: Blue cells = hardcoded inputs (edit these). All figures synthetic — Meridian is a fictional training company.

Sheet Revenue
A1: Revenue Forecast ($000s)
A3: Line item | B3: 2026 | C3: 2027 | D3: 2028 | E3: 2029 | F3: 2030
A4: Gold revenue | B4: =Assumptions!B4*Assumptions!B6 -> 768000 | C4: =B4*(1+Assumptions!$B$8) -> 798720 | D4: =C4*(1+Assumptions!$B$8) -> 830668.8 | E4: =D4*(1+Assumptions!$B$8) -> 863895.55 | F4: =E4*(1+Assumptions!$B$8) -> 898451.37
A5: Copper revenue | B5: =Assumptions!B5*Assumptions!B7*1000/1000 -> 427.5 | C5: =B5*(1+Assumptions!$B$8) -> 444.6 | D5: =C5*(1+Assumptions!$B$8) -> 462.384 | E5: =D5*(1+Assumptions!$B$8) -> 480.87936 | F5: =E5*(1+Assumptions!$B$8) -> 500.11453
A6: Total revenue | B6: =B4+B5 -> 768427.5 | C6: =C4+C5 -> 799164.6 | D6: =D4+D5 -> 831131.18 | E6: =E4+E5 -> 864376.43 | F6: =F4+F5 -> 898951.49

Sheet CashFlow
A1: Free Cash Flow ($000s)
A3: Line item | B3: 2026 | C3: 2027 | D3: 2028 | E3: 2029 | F3: 2030
A4: Total revenue | B4: =Revenue!B6 -> 768427.5 | C4: =Revenue!C6 -> 799164.6 | D4: =Revenue!D6 -> 831131.18 | E4: =Revenue!E6 -> 864376.43 | F4: =Revenue!F6 -> 898951.49
A5: Operating costs | B5: =-Assumptions!$B$9*Assumptions!$B$6 -> -432000 | C5: =B5*(1+Assumptions!$B$10) -> -444960 | D5: =-#REF!*(1+Assumptions!$B$10) -> #REF! | E5: =D5*(1+Assumptions!$B$10) -> #REF! | F5: =E5*(1+Assumptions!$B$10) -> #REF!
A6: EBITDA | B6: =B4+B5 -> 336427.5 | C6: =C4+C5 -> 354204.6 | D6: =D4+D5 -> #REF! | E6: =E4+E5 -> #REF! | F6: =F4+F5 -> #REF!
A7: Tax | B7: =-B6*Assumptions!$B$11 -> -94199.7 | C7: =-C6*Assumptions!$B$11 -> -99177.288 | D7: =-D6*Assumptions!$B$11 -> #REF! | E7: =-E6*Assumptions!$B$11 -> #REF! | F7: =-F6*Assumptions!$B$11 -> #REF!
A8: Capex | B8: -85000 | C8: =B8 -> -85000 | D8: =C8 -> -85000 | E8: =D8 -> -85000 | F8: =E8 -> -85000
A9: Free cash flow | B9: =B6+B7+B8 -> 157227.8 | C9: =C6+C7+C8 -> 170027.31 | D9: =D6+D7+D8 -> #REF! | E9: =E6+E7+E8 -> #REF! | F9: =F6+F7+F8 -> #REF!

Sheet Valuation
A1: DCF Valuation ($000s)
A2: Item | B2: Value
A3: Final-year FCF (2030) | B3: =CashFlow!F9 -> #REF!
A4: Terminal growth rate | B4: =Assumptions!B13 -> 0.02
A5: Discount rate (WACC) | B5: =Assumptions!B12 -> 0.09
A6: Terminal value = FCF×(1+g)/(WACC−g) | B6: =B3*(1+B4)/(B5-B4) -> #REF!
A7: Discount factor (yr 5) | B7: =1/(1+B5)^5 -> 0.64993139
A8: PV of terminal value | B8: =B6*B7 -> #REF!
A9: PV of forecast FCF (2026–2030) | B9: =NPV(B5,CashFlow!B9:F9) -> #REF!
A10: Enterprise value | B10: =B8+B9 -> #REF!
